.gitignore
CHANGES.txt
CONTRIBUTORS.txt
MANIFEST.in
README.rst
bootstrap.py
buildout.cfg
setup.py
collective/__init__.py
collective.js.detectmobilebrowsers.egg-info/PKG-INFO
collective.js.detectmobilebrowsers.egg-info/SOURCES.txt
collective.js.detectmobilebrowsers.egg-info/dependency_links.txt
collective.js.detectmobilebrowsers.egg-info/entry_points.txt
collective.js.detectmobilebrowsers.egg-info/namespace_packages.txt
collective.js.detectmobilebrowsers.egg-info/not-zip-safe
collective.js.detectmobilebrowsers.egg-info/requires.txt
collective.js.detectmobilebrowsers.egg-info/top_level.txt
collective/js/__init__.py
collective/js/detectmobilebrowsers/__init__.py
collective/js/detectmobilebrowsers/configure.zcml
collective/js/detectmobilebrowsers/detectmobilebrowsers.js
collective/js/detectmobilebrowsers/interfaces.py
collective/js/detectmobilebrowsers/upgrades.py
collective/js/detectmobilebrowsers/upgrades.zcml
collective/js/detectmobilebrowsers/example/__init__.py
collective/js/detectmobilebrowsers/example/configure.zcml
collective/js/detectmobilebrowsers/example/detectmobilebrowsers.pt
collective/js/detectmobilebrowsers/profiles/default/jsregistry.xml
collective/js/detectmobilebrowsers/profiles/default/metadata.xml
collective/js/detectmobilebrowsers/profiles/default/registry.xml
docs/HISTORY.txt
docs/LICENSE.txt